<SLO_CelPracyArchiwalny>
        <entry>
            <key>100102</key>
            <value>INWENTARYZACJA POWYKONAWCZA</value>
        </entry>
        <entry>
            <key>100109</key>
            <value>wytyczenie budynków</value>
        </entry>
        <entry>
            <key>100001</key>
            <value>pomiar sytacyjno-wysokościowy</value>
        </entry>
        <entry>
            <key>100003</key>
            <value>inwentaryzacja wodociągu</value>
        </entry>
        <entry>
            <key>100002</key>
            <value>mapa do celów projektowych </value>
        </entry>
        <entry>
            <key>100005</key>
            <value>wznowienie granic</value>
        </entry>
        <entry>
            <key>100006</key>
            <value>rozgraniczenie gruntów</value>
        </entry>
        <entry>
            <key>100009</key>
            <value>inwentaryzacja telefonu</value>
        </entry>
        <entry>
            <key>100008</key>
            <value>inwentaryzacja kanalizacji</value>
        </entry>
        <entry>
            <key>100011</key>
            <value>inwentaryzacja gazu</value>
        </entry>
        <entry>
            <key>100013</key>
            <value>mapa numeryczna ewidencji gruntów</value>
        </entry>
        <entry>
            <key>100012</key>
            <value>osnowa</value>
        </entry>
        <entry>
            <key>100014</key>
            <value>modernizacja mapy syt-wys 1:1000</value>
        </entry>
        <entry>
            <key>100017</key>
            <value>aktualizacja mapy syt-wys   BEZ  ZMIAN</value>
        </entry>
        <entry>
            <key>100019</key>
            <value>podział</value>
        </entry>
        <entry>
            <key>100018</key>
            <value>opracowanie do celów prawnych</value>
        </entry>
        <entry>
            <key>100027</key>
            <value>inwentaryzacja CO</value>
        </entry>
        <entry>
            <key>100029</key>
            <value>aktualizacja ewidencji gruntów i budynków</value>
        </entry>
        <entry>
            <key>100028</key>
            <value>aktualizacja mapy glebowo-rolniczej</value>
        </entry>
        <entry>
            <key>100031</key>
            <value>ustalenie położenia pkt.węzłowych granic powiatu</value>
        </entry>
        <entry>
            <key>100047</key>
            <value>inwentaryzacja budynku</value>
        </entry>
        <entry>
            <key>100049</key>
            <value>inwentaryzacja kabla energetycznego</value>
        </entry>
        <entry>
            <key>100055</key>
            <value>klasyfikacja gruntów</value>
        </entry>
        <entry>
            <key>100057</key>
            <value>wymiana gruntów</value>
        </entry>
        <entry>
            <key>100056</key>
            <value>połączenie działek</value>
        </entry>
        <entry>
            <key>100059</key>
            <value>inwentaryzacja kabla telewizyjnego</value>
        </entry>
        <entry>
            <key>100058</key>
            <value>weryfikacja ewidencji gruntów</value>
        </entry>
        <entry>
            <key>100061</key>
            <value>ewidencja budynków</value>
        </entry>
        <entry>
            <key>100066</key>
            <value>scalenie</value>
        </entry>
        <entry>
            <key>100</key>
            <value>utworzenie bazy danych państwowego rejestru podstawowych osnów geodezyjnych, grawimetrycznych i magnetycznych (PRPOG)</value>
        </entry>
        <entry>
            <key>101</key>
            <value>aktualizacja bazy danych państwowego rejestru podstawowych osnów geodezyjnych, grawimetrycznych i magnetycznych (PRPOG) Dziennik Ustaw – 35 – Poz. 1183</value>
        </entry>
        <entry>
            <key>102</key>
            <value>utworzenie bazy danych obiektów topograficznych o szczegółowości zapewniającej tworzenie standardowych opracowań kartograficznych w skalach 1:10 000–1:100 000, w tym kartograficznych opracowań numerycznego modelu rzeźby terenu (BDOT10k)</value>
        </entry>
        <entry>
            <key>103</key>
            <value>aktualizacja bazy danych obiektów topograficznych o szczegółowości zapewniającej tworzenie standardowych opracowań kartograficznych w skalach 1:10 000–1:100 000, w tym kartograficznych opracowań numerycznego modelu rzeźby terenu (BDOT10k)</value>
        </entry>
        <entry>
            <key>104</key>
            <value>utworzenie bazy danych obiektów ogólnogeograficznych o szczegółowości zapewniającej tworzenie standardowych opracowań kartograficznych w skalach 1:250 000 i mniejszych, w tym kartograficznych opracowań numerycznego modelu rzeźby terenu (BDOO)</value>
        </entry>
        <entry>
            <key>105</key>
            <value>aktualizacja bazy danych obiektów ogólnogeograficznych o szczegółowości zapewniającej tworzenie standardowych opracowań kartograficznych w skalach 1:250 000 i mniejszych, w tym kartograficznych opracowań numerycznego modelu rzeźby terenu (BDOO)</value>
        </entry>
        <entry>
            <key>106</key>
            <value>utworzenie krajowej bazy danych geodezyjnej ewidencji sieci uzbrojenia terenu (K-GESUT)</value>
        </entry>
        <entry>
            <key>100075</key>
            <value>AKTUALIZACJA MAPY SYT-WYS</value>
        </entry>
        <entry>
            <key>107</key>
            <value>aktualizacja krajowej bazy danych geodezyjnej ewidencji sieci uzbrojenia terenu (K-GESUT)</value>
        </entry>
        <entry>
            <key>108</key>
            <value>utworzenie bazy danych zintegrowanych kopii baz danych BDOT10k</value>
        </entry>
        <entry>
            <key>109</key>
            <value>aktualizacja bazy danych zintegrowanych kopii baz danych BDOT10k</value>
        </entry>
        <entry>
            <key>110</key>
            <value>utworzenie bazy danych państwowego rejestru granic i powierzchni jednostek podziałów terytorialnych kraju (PRG) Dziennik Ustaw – 36 – Poz. 1183</value>
        </entry>
        <entry>
            <key>111</key>
            <value>aktualizacja bazy danych państwowego rejestru granic i powierzchni jednostek podziałów terytorialnych kraju (PRG)</value>
        </entry>
        <entry>
            <key>100078</key>
            <value>URZĄDZANIE LASU</value>
        </entry>
        <entry>
            <key>112</key>
            <value>utworzenie bazy danych państwowego rejestru nazw geograficznych (PRNG)</value>
        </entry>
        <entry>
            <key>100081</key>
            <value>POMIAR UZUPEŁNIAJĄCY</value>
        </entry>
        <entry>
            <key>113</key>
            <value>aktualizacja bazy danych państwowego rejestru nazw geograficznych (PRNG)</value>
        </entry>
        <entry>
            <key>100080</key>
            <value>POMIAR DLA BANKU</value>
        </entry>
        <entry>
            <key>114</key>
            <value>utworzenie bazy danych ortofotomapy</value>
        </entry>
        <entry>
            <key>100083</key>
            <value>USTALENIE GRANIC</value>
        </entry>
        <entry>
            <key>115</key>
            <value>utworzenie bazy danych numerycznego modelu terenu (NMT)</value>
        </entry>
        <entry>
            <key>100089</key>
            <value>WYWŁASZCZENIE</value>
        </entry>
    </SLO_CelPracyArchiwalny>